[
  {
    "id": "copper-trail-brewing-co",
    "name": "Copper Trail Brewing Co.",
    "brewery_type": "micro",
    "street": "410 30th Ave E Ste 103",
    "city": "Alexandria",
    "state": "Minnesota",
    "postal_code": "56308-4770",
    "website_url": "http://www.coppertrailbrewing.com",
    "phone": "3202196688",
    "created_at": "2018-07-24 01:33:38.249249",
    "updated_at": "2018-08-11 21:38:01.146751",
    "country": "United States",
    "longitude": "",
    "latitude": "",
    "tags": []
  }
]