[
  {
    "id": "fury-brewing-company",
    "name": "Fury Brewing Company",
    "brewery_type": "micro",
    "street": "13380 US-30",
    "city": "Irwin",
    "state": "Pennsylvania",
    "postal_code": "15642",
    "website_url": "http://www.furybrewingcompany.com",
    "phone": "7248265162",
    "created_at": "2018-07-24 01:34:10.616947",
    "updated_at": "2018-08-24 16:08:46.654914",
    "country": "United States",
    "longitude": "-79.7029626",
    "latitude": "40.3248479",
    "tags": []
  },
  {
    "id": "quinn-brewing-company",
    "name": "Quinn Brewing Company",
    "brewery_type": "micro",
    "street": "3000 Commerce Loop Ste 3200",
    "city": "Irwin",
    "state": "Pennsylvania",
    "postal_code": "15642-8112",
    "website_url": "http://www.quinnbrewing.com",
    "phone": "7245905916",
    "created_at": "2018-07-24 01:34:12.09256",
    "updated_at": "2018-08-11 21:39:30.070977",
    "country": "United States",
    "longitude": "",
    "latitude": "",
    "tags": []
  }
]