[
  {
    "id": "three-bridges-brewing-/-off-the-wagon-brewery",
    "name": "Three Bridges Brewing / Off the Wagon Brewery",
    "brewery_type": "brewpub",
    "street": "2107 Tamiami Trl S",
    "city": "Venice",
    "state": "Florida",
    "postal_code": "34293-5011",
    "website_url": "http://www.otwbar.com",
    "phone": "9414972048",
    "created_at": "2018-07-24 01:33:14.928939",
    "updated_at": "2018-08-24 00:28:41.193393",
    "country": "United States",
    "longitude": "-82.3913649",
    "latitude": "27.0497931",
    "tags": []
  }
]